{
    "AC": "10",
    "Base": "spiritual",
    "Description": "Large spiritual (R)",
    "Detail": "Fly",
    "EV": "5",
    "Emote": "Silent",
    "HD": "7",
    "HP": "385",
    "Habitat": "Land",
    "Holy": "Demonic",
    "Hurt0": "17:Fire",
    "Hurt1": "",
    "Hurt2": "",
    "Intelligence": "Human",
    "Name": "efreet",
    "Resistance": "poison:fire:VC",
    "Shoot": "",
    "Size": "Large",
    "Speed": "10",
    "Spell": "",
    "Tile": "MONS_EFREET",
    "Use": "MonEquipment",
    "WP": "20"
}